{"version":1,"resource":"file:///home/offlinebot/.config/ags/style/menu.css","entries":[{"id":"Rt7g.css","timestamp":1725506986576},{"id":"BINL.css","timestamp":1725507334833},{"id":"URx3.css","timestamp":1725507382371},{"id":"zr8G.css","timestamp":1725507399141},{"id":"l9DC.css","timestamp":1725507638972},{"id":"3tfG.css","timestamp":1725507653893},{"id":"5bYb.css","timestamp":1725508022773},{"id":"Vj0u.css","timestamp":1725508034650},{"id":"Jk2j.css","timestamp":1725559571532},{"id":"8ZsD.css","timestamp":1725559702116},{"id":"bWHy.css","timestamp":1725560367134},{"id":"Z5hP.css","timestamp":1725560385528},{"id":"feox.css","timestamp":1725560411220},{"id":"NhuW.css","timestamp":1725560430537},{"id":"dtLI.css","timestamp":1725560466386},{"id":"OyOz.css","timestamp":1725560512895},{"id":"GunU.css","timestamp":1725560557047},{"id":"rPvC.css","timestamp":1725560569492},{"id":"OttG.css","timestamp":1725560600221},{"id":"AH1I.css","timestamp":1725560624272},{"id":"j7ZL.css","timestamp":1725560663009},{"id":"8Sat.css","timestamp":1725560709021},{"id":"yKcD.css","timestamp":1725560719638},{"id":"kqam.css","timestamp":1725560745084},{"id":"4H0U.css","timestamp":1725568045093},{"id":"bHDr.css","timestamp":1725568081428},{"id":"uMkc.css","timestamp":1725568108225},{"id":"ID93.css","timestamp":1725568233720},{"id":"Wa1a.css","timestamp":1725568274436},{"id":"otpx.css","timestamp":1725568288418},{"id":"y7eq.css","timestamp":1725568303350},{"id":"eFZA.css","timestamp":1725568326856},{"id":"OTPt.css","timestamp":1725568341832},{"id":"eJcg.css","timestamp":1725568406354},{"id":"bSEz.css","timestamp":1725568491669},{"id":"68m1.css","timestamp":1725568507121},{"id":"uySp.css","timestamp":1725568610908},{"id":"ORem.css","timestamp":1725568626762},{"id":"5cPQ.css","timestamp":1725568699651},{"id":"E7DX.css","timestamp":1725568710496},{"id":"oXiK.css","timestamp":1725568725793},{"id":"0opV.css","timestamp":1725568760344},{"id":"UABN.css","timestamp":1725568770958},{"id":"DyDe.css","timestamp":1725568958498},{"id":"3cRC.css","timestamp":1725568980856},{"id":"CXpN.css","timestamp":1725568998884},{"id":"S1n1.css","timestamp":1725569011694},{"id":"RS3O.css","timestamp":1725569030808},{"id":"9z6x.css","timestamp":1725569042142},{"id":"Sj97.css","timestamp":1725569090917}]}