{"version":1,"resource":"file:///home/offlinebot/.config/ags/windows/logout/logout.js","entries":[{"id":"QH5g.js","timestamp":1725484403922},{"id":"GSZg.js","timestamp":1725484477062},{"id":"B0iL.js","timestamp":1725484496487},{"id":"7ura.js","timestamp":1725484543807},{"id":"RUNx.js","timestamp":1725484556248},{"id":"Qv1d.js","timestamp":1725484569065},{"id":"5NLH.js","timestamp":1725484604428},{"id":"Oo6U.js","timestamp":1725484670880},{"id":"4k4g.js","timestamp":1725484725482},{"id":"5jfb.js","timestamp":1725484752258},{"id":"xSWS.js","timestamp":1725484796729},{"id":"4YMr.js","timestamp":1725484832645},{"id":"nz1P.js","timestamp":1725484862455},{"id":"XAqz.js","timestamp":1725484890084},{"id":"qSqs.js","timestamp":1725484911275},{"id":"VTfQ.js","timestamp":1725485039640},{"id":"oPJa.js","timestamp":1725485072838},{"id":"uNj4.js","timestamp":1725485122676},{"id":"zj6n.js","timestamp":1725485142641},{"id":"NU66.js","timestamp":1725485163621},{"id":"E9x7.js","timestamp":1725485215672},{"id":"CDie.js","timestamp":1725485266927},{"id":"WLPG.js","timestamp":1725485320784},{"id":"zbZY.js","timestamp":1725485355620},{"id":"rZXj.js","timestamp":1725486764060},{"id":"Z3L9.js","timestamp":1725486820588},{"id":"tbny.js","timestamp":1725486832516},{"id":"eXgh.js","timestamp":1725486857529},{"id":"JdY0.js","timestamp":1725486873721},{"id":"JU5z.js","timestamp":1725486917941},{"id":"CEGZ.js","timestamp":1725486990022},{"id":"PoE5.js","timestamp":1725487015326},{"id":"rTvl.js","timestamp":1725487103298},{"id":"8GbQ.js","timestamp":1725487115682},{"id":"3SJD.js","timestamp":1725487318431},{"id":"rGtt.js","timestamp":1725491860002},{"id":"hKe0.js","timestamp":1725491939941},{"id":"7suF.js","timestamp":1725491980365},{"id":"1FiN.js","timestamp":1725491992424},{"id":"gO33.js","timestamp":1725492018660},{"id":"NeGB.js","timestamp":1725492031792},{"id":"sVTP.js","timestamp":1725494443732},{"id":"MkGn.js","timestamp":1725494463874},{"id":"lKtR.js","timestamp":1725494518682},{"id":"1dWP.js","timestamp":1725494638755},{"id":"PfVL.js","timestamp":1725494648891},{"id":"9Ekb.js","timestamp":1725494679839},{"id":"widg.js","timestamp":1725494759994},{"id":"FEL4.js","timestamp":1725502523963},{"id":"SV6W.js","source":"moved.source","sourceDescription":"~/.config/ags/logout/logout.js","timestamp":1725503285710}]}